MANIFEST.in
README.rst
setup.cfg
setup.py
contact_importer/__init__.py
contact_importer.egg-info/PKG-INFO
contact_importer.egg-info/SOURCES.txt
contact_importer.egg-info/dependency_links.txt
contact_importer.egg-info/entry_points.txt
contact_importer.egg-info/not-zip-safe
contact_importer.egg-info/requires.txt
contact_importer.egg-info/top_level.txt
contact_importer/lib/__init__.py
contact_importer/lib/oauth1.py
contact_importer/providers/__init__.py
contact_importer/providers/base.py
contact_importer/providers/google.py
contact_importer/providers/live.py
contact_importer/providers/yahoo.py