Metadata-Version: 1.0
Name: contact-importer
Version: 0.0.1
Summary: Import Gmail, Live and Yahoo contacts within your Python application.
Home-page: UNKNOWN
Author: Unknown
Author-email: UNKNOWN
License: UNKNOWN
Platform: UNKNOWN
